geopack_tsyganenko.cpython-312-darwin.so
tsyganenko-2020.2.3.dist-info/RECORD
tsyganenko-2020.2.3.dist-info/WHEEL
tsyganenko-2020.2.3.dist-info/METADATA
tsyganenko-2020.2.3.dist-info/licenses/LICENCE.txt
tsyganenko/trace.py
tsyganenko/convert.py
tsyganenko/__init__.py
tsyganenko/.dylibs/libgfortran.5.dylib
tsyganenko/.dylibs/libquadmath.0.dylib
tsyganenko/.dylibs/libgcc_s.1.1.dylib
