Metadata-Version: 2.4
Name: tsyganenko
Version: 2020.2.3
Summary: A Python wrapper for N A Tsyganenko’s field-line tracing routines.
Keywords: magnetic field,magnetosphere
Author: Sebastien de Larquier
Author-Email: John C Coxon <work@johncoxon.co.uk>
License-Expression: MIT
License-File: LICENCE.txt
Classifier: Development Status :: 4 - Beta
Classifier: Intended Audience :: Science/Research
Classifier: Natural Language :: English
Classifier: Programming Language :: Python :: 3
Classifier: Topic :: Scientific/Engineering :: Physics
Project-URL: Geopack, https://geo.phys.spbu.ru/~tsyganenko/empirical-models/
Project-URL: doi, https://doi.org/10.5281/zenodo.3937276
Project-URL: repository, https://github.com/johncoxon/tsyganenko
Requires-Python: >=3.12
Requires-Dist: matplotlib
Requires-Dist: numpy
Requires-Dist: pandas
Provides-Extra: notebook
Requires-Dist: jupyter; extra == "notebook"
